{
    "dummy_points": {
        "Q403Door": {
            "pos": {
                "x": 337.676,
                "y": -32.89,
                "z": 526.752
            },
            "rot": {
                "x": 0,
                "y": 220,
                "z": 0
            }
        },
        "Q46303NpcLaste": {
            "pos": {
                "x": 331.195,
                "y": -18.316,
                "z": 325.109
            },
            "rot": {
                "x": 0,
                "y": 296.573,
                "z": 0
            }
        },
        "Q463Born": {
            "pos": {
                "x": 338.932,
                "y": -18.959,
                "z": 352.815
            },
            "rot": {
                "x": 0,
                "y": 182.371,
                "z": 0
            }
        },
        "Q463Dummy": {
            "pos": {
                "x": 345.979,
                "y": -19.221,
                "z": 348.608
            },
            "rot": {
                "x": 0,
                "y": 0,
                "z": 0
            }
        },
        "Q463Kaeya": {
            "pos": {
                "x": 343.206,
                "y": -19.277,
                "z": 342.462
            },
            "rot": {
                "x": 0,
                "y": 182.069,
                "z": 0
            }
        },
        "Q463KaeyaBorn": {
            "pos": {
                "x": 343.296,
                "y": -19.277,
                "z": 356.607
            },
            "rot": {
                "x": 0,
                "y": 180.494,
                "z": 0
            }
        },
        "Q463NPC": {
            "pos": {
                "x": 345.242,
                "y": -19.247,
                "z": 339.931
            },
            "rot": {
                "x": 0,
                "y": 254.877,
                "z": 0
            }
        },
        "Q463NPCBorn": {
            "pos": {
                "x": 349.113,
                "y": -19.276,
                "z": 349.938
            },
            "rot": {
                "x": 0,
                "y": 207.566,
                "z": 0
            }
        },
        "Q463Paimon": {
            "pos": {
                "x": 340.632,
                "y": -19.277,
                "z": 340.08
            },
            "rot": {
                "x": 0,
                "y": 26,
                "z": 0
            }
        },
        "Q463Player": {
            "pos": {
                "x": 341.829,
                "y": -19.221,
                "z": 338.746
            },
            "rot": {
                "x": 0,
                "y": 15.594,
                "z": 0
            }
        },
        "Q463Soldier": {
            "pos": {
                "x": 344.261,
                "y": -19.276,
                "z": 345.032
            },
            "rot": {
                "x": 0,
                "y": 180.247,
                "z": 0
            }
        },
        "Q463Soldier2": {
            "pos": {
                "x": 343.021,
                "y": -19.277,
                "z": 344.842
            },
            "rot": {
                "x": 0,
                "y": 184.632,
                "z": 0
            }
        },
        "Q463Soldier3": {
            "pos": {
                "x": 345.835,
                "y": -19.277,
                "z": 341.045
            },
            "rot": {
                "x": 0,
                "y": 213.051,
                "z": 0
            }
        },
        "Q463Soldier4": {
            "pos": {
                "x": 344.511,
                "y": -19.277,
                "z": 338.846
            },
            "rot": {
                "x": 0,
                "y": 37.157,
                "z": 0
            }
        },
        "Q463SoldierBorn": {
            "pos": {
                "x": 344.542,
                "y": -18.889,
                "z": 360.509
            },
            "rot": {
                "x": 0,
                "y": 185.292,
                "z": 0
            }
        },
        "Q463SoldierBorn2": {
            "pos": {
                "x": 342.105,
                "y": -19.004,
                "z": 360.615
            },
            "rot": {
                "x": 0,
                "y": 180.535,
                "z": 0
            }
        },
        "Q463Trap": {
            "pos": {
                "x": 343.119,
                "y": -18.372,
                "z": 324.801
            },
            "rot": {
                "x": 0,
                "y": 168.345,
                "z": 0
            }
        }
    }
}