{
    "action_EVENT_ENTER_REGION_134004": "WARN: Lua function omitted from the dump",
    "action_EVENT_LEAVE_REGION_134006": "WARN: Lua function omitted from the dump",
    "action_EVENT_SELECT_OPTION_134005": "WARN: Lua function omitted from the dump",
    "condition_EVENT_ENTER_REGION_134004": "WARN: Lua function omitted from the dump",
    "condition_EVENT_LEAVE_REGION_134006": "WARN: Lua function omitted from the dump",
    "condition_EVENT_SELECT_OPTION_134005": "WARN: Lua function omitted from the dump",
    "gadgets": [
        {
            "area_id": 17,
            "config_id": 134001,
            "gadget_id": 70350004,
            "level": 30,
            "persistent": true,
            "pos": {
                "x": -3534.108,
                "y": 183.01,
                "z": -1173.5
            },
            "rot": {
                "x": 0,
                "y": 312.156,
                "z": 90
            }
        },
        {
            "area_id": 17,
            "config_id": 134002,
            "gadget_id": 70350004,
            "level": 30,
            "persistent": true,
            "pos": {
                "x": -3534.108,
                "y": 177.411,
                "z": -1173.5
            },
            "rot": {
                "x": 0,
                "y": 312.156,
                "z": 90
            }
        },
        {
            "area_id": 17,
            "config_id": 134003,
            "gadget_id": 70360170,
            "level": 30,
            "persistent": true,
            "pos": {
                "x": -3533.847,
                "y": 178.735,
                "z": -1172.241
            },
            "rot": {
                "x": 270,
                "y": 132.156,
                "z": 0
            }
        }
    ],
    "init_config": {
        "end_suite": 0,
        "io_type": 1,
        "rand_suite": false,
        "suite": 1
    },
    "monsters": [],
    "npcs": [],
    "regions": [
        {
            "area_id": 17,
            "config_id": 134004,
            "pos": {
                "x": -3536.583,
                "y": 176.349,
                "z": -1169.824
            },
            "radius": 4,
            "shape": 1
        },
        {
            "area_id": 17,
            "config_id": 134006,
            "pos": {
                "x": -3536.583,
                "y": 176.349,
                "z": -1169.824
            },
            "radius": 4,
            "shape": 1
        }
    ],
    "suite_disk": [
        {
            "gadgets": [
                {
                    "config_id": 134001,
                    "state": 0
                },
                {
                    "config_id": 134002,
                    "state": 0
                },
                {
                    "config_id": 134003,
                    "state": 0
                }
            ],
            "monsters": [],
            "npcs": [],
            "regions": [
                134004,
                134006
            ],
            "triggers": [
                "ENTER_REGION_134004",
                "SELECT_OPTION_134005",
                "LEAVE_REGION_134006"
            ],
            "variables": []
        },
        {
            "gadgets": [
                {
                    "config_id": 134001,
                    "state": 201
                },
                {
                    "config_id": 134002,
                    "state": 201
                },
                {
                    "config_id": 134003,
                    "state": 201
                }
            ],
            "monsters": [],
            "npcs": [],
            "regions": [],
            "triggers": [],
            "variables": []
        }
    ],
    "suites": [
        {
            "gadgets": [
                134001,
                134002,
                134003
            ],
            "monsters": [],
            "rand_weight": 100,
            "regions": [
                134004,
                134006
            ],
            "triggers": [
                "ENTER_REGION_134004",
                "SELECT_OPTION_134005",
                "LEAVE_REGION_134006"
            ]
        },
        {
            "gadgets": [
                134001,
                134002,
                134003
            ],
            "monsters": [],
            "rand_weight": 100,
            "regions": [],
            "triggers": []
        }
    ],
    "triggers": [
        {
            "action": "action_EVENT_ENTER_REGION_134004",
            "condition": "condition_EVENT_ENTER_REGION_134004",
            "config_id": 1134004,
            "event": 4,
            "name": "ENTER_REGION_134004",
            "source": "",
            "trigger_count": 0
        },
        {
            "action": "action_EVENT_SELECT_OPTION_134005",
            "condition": "condition_EVENT_SELECT_OPTION_134005",
            "config_id": 1134005,
            "event": 9,
            "name": "SELECT_OPTION_134005",
            "source": "",
            "trigger_count": 0
        },
        {
            "action": "action_EVENT_LEAVE_REGION_134006",
            "condition": "condition_EVENT_LEAVE_REGION_134006",
            "config_id": 1134006,
            "event": 5,
            "name": "LEAVE_REGION_134006",
            "source": "",
            "trigger_count": 0
        }
    ],
    "variables": []
}