{
    "gadgets": [],
    "init_config": {
        "end_suite": 0,
        "rand_suite": false,
        "suite": 1
    },
    "monsters": [
        {
            "area_id": 6,
            "config_id": 89001,
            "drop_tag": "\u9e1f\u7c7b",
            "level": 24,
            "monster_id": 28030402,
            "pos": {
                "x": 645.819,
                "y": 185.689,
                "z": 1118.138
            },
            "rot": {
                "x": 0,
                "y": 0,
                "z": 0
            }
        },
        {
            "area_id": 6,
            "config_id": 89002,
            "drop_tag": "\u9e1f\u7c7b",
            "level": 24,
            "monster_id": 28030402,
            "pos": {
                "x": 643.432,
                "y": 186.205,
                "z": 1118.56
            },
            "rot": {
                "x": 0,
                "y": 293.656,
                "z": 0
            }
        },
        {
            "area_id": 6,
            "config_id": 89003,
            "drop_tag": "\u9e1f\u7c7b",
            "level": 24,
            "monster_id": 28030404,
            "pos": {
                "x": 643.658,
                "y": 185.692,
                "z": 1120.599
            },
            "rot": {
                "x": 0,
                "y": 196.783,
                "z": 0
            }
        }
    ],
    "npcs": [],
    "regions": [],
    "suites": [
        {
            "gadgets": [],
            "monsters": [
                89001,
                89002,
                89003
            ],
            "rand_weight": 100,
            "regions": [],
            "triggers": []
        }
    ],
    "triggers": [],
    "variables": []
}