{
    "action_EVENT_CHALLENGE_FAIL_77013": "WARN: Lua function omitted from the dump",
    "action_EVENT_CHALLENGE_SUCCESS_77012": "WARN: Lua function omitted from the dump",
    "action_EVENT_GADGET_CREATE_77016": "WARN: Lua function omitted from the dump",
    "action_EVENT_GADGET_STATE_CHANGE_77014": "WARN: Lua function omitted from the dump",
    "action_EVENT_GROUP_LOAD_77018": "WARN: Lua function omitted from the dump",
    "action_EVENT_SELECT_OPTION_77017": "WARN: Lua function omitted from the dump",
    "condition_EVENT_GADGET_CREATE_77016": "WARN: Lua function omitted from the dump",
    "condition_EVENT_GADGET_STATE_CHANGE_77014": "WARN: Lua function omitted from the dump",
    "condition_EVENT_SELECT_OPTION_77017": "WARN: Lua function omitted from the dump",
    "gadgets": [
        {
            "area_id": 210,
            "config_id": 77001,
            "drop_tag": "\u6e0a\u4e0b\u5bab\u6d3b\u52a8\u4f4e\u7ea7\u7a3b\u59bb",
            "gadget_id": 70211160,
            "isOneoff": true,
            "level": 16,
            "persistent": true,
            "pos": {
                "x": 505.452,
                "y": 136.787,
                "z": -241.33
            },
            "rot": {
                "x": 0,
                "y": 0,
                "z": 0
            }
        },
        {
            "area_id": 210,
            "config_id": 77002,
            "gadget_id": 70350093,
            "level": 35,
            "persistent": true,
            "pos": {
                "x": 474.226,
                "y": 142.899,
                "z": -156.438
            },
            "rot": {
                "x": 0,
                "y": 0,
                "z": 0
            }
        },
        {
            "area_id": 210,
            "config_id": 77003,
            "gadget_id": 70360001,
            "level": 35,
            "persistent": true,
            "pos": {
                "x": 474.226,
                "y": 142.899,
                "z": -156.438
            },
            "rot": {
                "x": 0,
                "y": 0,
                "z": 0
            }
        },
        {
            "area_id": 210,
            "config_id": 77004,
            "gadget_id": 70290150,
            "level": 35,
            "pos": {
                "x": 489.938,
                "y": 145.733,
                "z": -157.136
            },
            "rot": {
                "x": 0,
                "y": 0,
                "z": 0
            }
        },
        {
            "area_id": 210,
            "config_id": 77005,
            "gadget_id": 70290150,
            "level": 35,
            "pos": {
                "x": 501.799,
                "y": 146.045,
                "z": -165.568
            },
            "rot": {
                "x": 0,
                "y": 0,
                "z": 0
            }
        },
        {
            "area_id": 210,
            "config_id": 77006,
            "gadget_id": 70290150,
            "level": 35,
            "pos": {
                "x": 513.077,
                "y": 145.801,
                "z": -174.205
            },
            "rot": {
                "x": 0,
                "y": 0,
                "z": 0
            }
        },
        {
            "area_id": 210,
            "config_id": 77007,
            "gadget_id": 70290150,
            "level": 35,
            "pos": {
                "x": 515.013,
                "y": 137.771,
                "z": -201.553
            },
            "rot": {
                "x": 0,
                "y": 0,
                "z": 0
            }
        },
        {
            "area_id": 210,
            "config_id": 77008,
            "gadget_id": 70290150,
            "level": 35,
            "pos": {
                "x": 513.728,
                "y": 136.117,
                "z": -220.843
            },
            "rot": {
                "x": 0,
                "y": 0,
                "z": 0
            }
        },
        {
            "area_id": 210,
            "config_id": 77009,
            "gadget_id": 70290150,
            "level": 35,
            "pos": {
                "x": 516.083,
                "y": 144.748,
                "z": -183.885
            },
            "rot": {
                "x": 0,
                "y": 0,
                "z": 0
            }
        },
        {
            "area_id": 210,
            "config_id": 77010,
            "gadget_id": 70290150,
            "level": 35,
            "pos": {
                "x": 512.578,
                "y": 137.204,
                "z": -226.937
            },
            "rot": {
                "x": 0,
                "y": 0,
                "z": 0
            }
        },
        {
            "area_id": 210,
            "config_id": 77011,
            "gadget_id": 70290150,
            "level": 35,
            "pos": {
                "x": 504.148,
                "y": 137.628,
                "z": -235.284
            },
            "rot": {
                "x": 0,
                "y": 0,
                "z": 0
            }
        }
    ],
    "init_config": {
        "end_suite": 3,
        "rand_suite": false,
        "suite": 1
    },
    "monsters": [],
    "npcs": [],
    "regions": [],
    "suites": [
        {
            "gadgets": [
                77002,
                77003
            ],
            "monsters": [],
            "rand_weight": 100,
            "regions": [],
            "triggers": [
                "CHALLENGE_SUCCESS_77012",
                "CHALLENGE_FAIL_77013",
                "GADGET_STATE_CHANGE_77014",
                "ANY_GADGET_DIE_77015",
                "GADGET_CREATE_77016",
                "SELECT_OPTION_77017",
                "GROUP_LOAD_77018"
            ]
        },
        {
            "gadgets": [
                77004,
                77005,
                77006,
                77007,
                77008,
                77009,
                77010,
                77011
            ],
            "monsters": [],
            "rand_weight": 100,
            "regions": [],
            "triggers": []
        },
        {
            "gadgets": [
                77002
            ],
            "monsters": [],
            "rand_weight": 100,
            "regions": [],
            "triggers": []
        }
    ],
    "triggers": [
        {
            "action": "action_EVENT_CHALLENGE_SUCCESS_77012",
            "condition": "",
            "config_id": 1077012,
            "event": 16,
            "name": "CHALLENGE_SUCCESS_77012",
            "source": "666",
            "trigger_count": 0
        },
        {
            "action": "action_EVENT_CHALLENGE_FAIL_77013",
            "condition": "",
            "config_id": 1077013,
            "event": 17,
            "name": "CHALLENGE_FAIL_77013",
            "source": "666",
            "trigger_count": 0
        },
        {
            "action": "action_EVENT_GADGET_STATE_CHANGE_77014",
            "condition": "condition_EVENT_GADGET_STATE_CHANGE_77014",
            "config_id": 1077014,
            "event": 7,
            "name": "GADGET_STATE_CHANGE_77014",
            "source": "",
            "trigger_count": 0
        },
        {
            "action": "",
            "condition": "",
            "config_id": 1077015,
            "event": 2,
            "name": "ANY_GADGET_DIE_77015",
            "source": "",
            "tag": "218",
            "trigger_count": 0
        },
        {
            "action": "action_EVENT_GADGET_CREATE_77016",
            "condition": "condition_EVENT_GADGET_CREATE_77016",
            "config_id": 1077016,
            "event": 6,
            "name": "GADGET_CREATE_77016",
            "source": "",
            "trigger_count": 0
        },
        {
            "action": "action_EVENT_SELECT_OPTION_77017",
            "condition": "condition_EVENT_SELECT_OPTION_77017",
            "config_id": 1077017,
            "event": 9,
            "name": "SELECT_OPTION_77017",
            "source": "",
            "trigger_count": 0
        },
        {
            "action": "action_EVENT_GROUP_LOAD_77018",
            "condition": "",
            "config_id": 1077018,
            "event": 29,
            "name": "GROUP_LOAD_77018",
            "source": "",
            "trigger_count": 0
        }
    ],
    "variables": []
}